grounder/__init__.py
grounder-0.0.1.dist-info/METADATA
grounder-0.0.1.dist-info/WHEEL
grounder-0.0.1.dist-info/RECORD
